<?xml version="1.0"?>
<page xmlns:xsi="http://www.w3.org/2001/XMLSchema-instance" layout="1column" xsi:noNamespaceSchemaLocation="urn:magento:framework:View/Layout/etc/page_configuration.xsd">
    <referenceContainer name="content.top">
        <block class="Astrio\TrainingModule1\Block\Block7" name="display_something" template="Astrio_TrainingModule1::template7.phtml" />
    </referenceContainer>
    <referenceBlock name="display_something">
        <arguments>
            <argument name="background_color" xsi:type="string">lightskyblue</argument>
        </arguments>
    </referenceBlock>

</page>
